HTMACat/Base_tools.py
HTMACat/Extract_info.py
HTMACat/IO.py
HTMACat/__init__.py
HTMACat/__version__.py
HTMACat/command.py
HTMACat/configuration.py
HTMACat/NEB/Construct_neb.py
HTMACat/NEB/Construct_network.py
HTMACat/NEB/Dismove.py
HTMACat/NEB/Post_struc.py
HTMACat/NEB/__init__.py
HTMACat/NEB/post_neb.py
HTMACat/NEB/vaspneb6.py
HTMACat/catkit/__init__.py
HTMACat/catkit/build.py
HTMACat/catkit/gratoms.py
HTMACat/catkit/readme.txt
HTMACat/catkit/data/__init__.py
HTMACat/catkit/data/fingerprints.db
HTMACat/catkit/data/properties.json
HTMACat/catkit/gen/__init__.py
HTMACat/catkit/gen/adsorption.py
HTMACat/catkit/gen/surface.py
HTMACat/catkit/gen/symmetry.py
HTMACat/catkit/gen/utils/__init__.py
HTMACat/catkit/gen/utils/connectivity.py
HTMACat/catkit/gen/utils/coordinates.py
HTMACat/catkit/gen/utils/graph.py
HTMACat/catkit/gen/utils/utilities.py
HTMACat/catkit/gen/utils/utils_mdnm.py
HTMACat/catkit/gen/utils/vectors.py
HTMACat/descriptor/Construct_descriptor.py
HTMACat/descriptor/Construct_descriptor_NEB.py
HTMACat/descriptor/Construct_descriptor_coad.py
HTMACat/descriptor/Construct_descriptor_surface.py
HTMACat/descriptor/Construct_descriptor_surface_single.py
HTMACat/descriptor/Element_Info
HTMACat/descriptor/__init__.py
HTMACat/model/Ads.py
HTMACat/model/Construct_adsorption_yaml.py
HTMACat/model/Species.py
HTMACat/model/Structure.py
HTMACat/model/Substrate.py
HTMACat/model/__init__.py
HTMACat/post/Extract_adener.py
HTMACat/post/Extract_adener_alloy.py
HTMACat/post/Extract_adener_site.py
HTMACat/post/Extract_cal_fre.py
HTMACat/post/__init__.py
HTMACat/post/cal_adsE.py
HTMACat-1.0.5.dist-info/LICENSE
HTMACat-1.0.5.dist-info/METADATA
HTMACat-1.0.5.dist-info/WHEEL
HTMACat-1.0.5.dist-info/entry_points.txt
HTMACat-1.0.5.dist-info/top_level.txt
HTMACat-1.0.5.dist-info/RECORD
