Metadata-Version: 2.1
Name: HTMACat
Version: 1.0.5
Summary: A high-throughput modeling, calculation, and analysis framework for catalytic reaction processes.
Home-page: https://stanfordbshan.github.io/HTMACat-kit/
Author: Jiaqiang Yang, Feifeng Wu, Zhaojie Wang, Yuxiao Lan, Haojie Li, Zhang Liu, Zhihong Zhang, Bin Shan*
Author-email: bshan@mail.hust.edu.cn
License: GPLv3
Keywords: high-throughput,python,catalysis,modeling
Platform: UNKNOWN
Classifier: Development Status :: 3 - Alpha
Classifier: Environment :: Console
Classifier: Operating System :: OS Independent
Requires-Python: >=3.6
Requires-Dist: ase (>=3.19)
Requires-Dist: numpy (>=1.20.0)
Requires-Dist: networkx (>=2.1)
Requires-Dist: scipy (>=0.1)
Requires-Dist: spglib (>=0.1)
Requires-Dist: ruamel.yaml (>0.15)
Requires-Dist: rdkit (>=2022.3.3)
Requires-Dist: typer[all] (>=0.6)
Requires-Dist: scikit-learn (>=1.0.1)
